{
  "updated": "2026-03-11T22:00:00.000Z",
  "airports": {
    "KPOC": {
      "name": "Brackett Field",
      "metar": "METAR KPOC 112147Z 24006KT 10SM CLR 24/09 A3021",
      "metarTime": "2026-03-11T22:00:00.000Z",
      "taf": "",
      "tafTime": ""
    },
    "KCCB": {
      "name": "Cable Airport",
      "metar": "METAR KCCB 112155Z AUTO 26008KT 10SM CLR 25/08 A3021 RMK AO2",
      "metarTime": "2026-03-11T22:00:00.000Z",
      "taf": "",
      "tafTime": ""
    },
    "KRAL": {
      "name": "Riverside Municipal",
      "metar": "METAR KRAL 112153Z VRB05KT 10SM CLR 27/09 A3019 RMK AO2 SLP209 T02670089",
      "metarTime": "2026-03-11T22:00:00.000Z",
      "taf": "",
      "tafTime": ""
    }
  }
}
