{
  "updated": "2026-06-11T11:16:14.095Z",
  "winds": {
    "ONT_06": [
      {
        "dir": "L&V",
        "speed": "<5",
        "temp": null
      },
      {
        "dir": "L&V",
        "speed": "<5",
        "temp": 23
      },
      {
        "dir": "L&V",
        "speed": "<5",
        "temp": 17
      },
      {
        "dir": "L&V",
        "speed": "<5",
        "temp": 12
      },
      {
        "dir": 250,
        "speed": 10,
        "temp": -3
      },
      {
        "dir": 310,
        "speed": 17,
        "temp": -17
      }
    ],
    "WJF_06": [
      {
        "dir": 340,
        "speed": 5,
        "temp": 22
      },
      {
        "dir": 340,
        "speed": 5,
        "temp": 22
      },
      {
        "dir": 340,
        "speed": 5,
        "temp": 18
      },
      {
        "dir": 260,
        "speed": 5,
        "temp": 11
      },
      {
        "dir": 250,
        "speed": 8,
        "temp": -4
      },
      {
        "dir": 300,
        "speed": 22,
        "temp": -17
      }
    ],
    "SBA_06": [
      {
        "dir": "L&V",
        "speed": "<5",
        "temp": null
      },
      {
        "dir": 10,
        "speed": 12,
        "temp": 22
      },
      {
        "dir": 10,
        "speed": 11,
        "temp": 17
      },
      {
        "dir": 360,
        "speed": 6,
        "temp": 11
      },
      {
        "dir": 300,
        "speed": 5,
        "temp": -4
      },
      {
        "dir": 300,
        "speed": 24,
        "temp": -17
      }
    ],
    "SAN_06": [
      {
        "dir": "L&V",
        "speed": "<5",
        "temp": null
      },
      {
        "dir": "L&V",
        "speed": "<5",
        "temp": 22
      },
      {
        "dir": 170,
        "speed": 7,
        "temp": 17
      },
      {
        "dir": "L&V",
        "speed": "<5",
        "temp": 11
      },
      {
        "dir": 90,
        "speed": 5,
        "temp": -4
      },
      {
        "dir": 360,
        "speed": 13,
        "temp": -18
      }
    ],
    "ONT_12": [
      {
        "dir": "L&V",
        "speed": "<5",
        "temp": null
      },
      {
        "dir": 120,
        "speed": 9,
        "temp": 21
      },
      {
        "dir": 150,
        "speed": 11,
        "temp": 16
      },
      {
        "dir": 160,
        "speed": 8,
        "temp": 9
      },
      {
        "dir": 270,
        "speed": 13,
        "temp": -4
      },
      {
        "dir": 320,
        "speed": 15,
        "temp": -17
      }
    ],
    "WJF_12": [
      {
        "dir": 80,
        "speed": 8,
        "temp": 21
      },
      {
        "dir": 80,
        "speed": 8,
        "temp": 21
      },
      {
        "dir": 160,
        "speed": 9,
        "temp": 16
      },
      {
        "dir": 200,
        "speed": 6,
        "temp": 10
      },
      {
        "dir": 290,
        "speed": 10,
        "temp": -5
      },
      {
        "dir": 300,
        "speed": 16,
        "temp": -17
      }
    ],
    "SBA_12": [
      {
        "dir": "L&V",
        "speed": "<5",
        "temp": null
      },
      {
        "dir": 110,
        "speed": 8,
        "temp": 21
      },
      {
        "dir": 100,
        "speed": 5,
        "temp": 16
      },
      {
        "dir": "L&V",
        "speed": "<5",
        "temp": 10
      },
      {
        "dir": 300,
        "speed": 9,
        "temp": -5
      },
      {
        "dir": 300,
        "speed": 21,
        "temp": -17
      }
    ],
    "SAN_12": [
      {
        "dir": "L&V",
        "speed": "<5",
        "temp": null
      },
      {
        "dir": 170,
        "speed": 10,
        "temp": 22
      },
      {
        "dir": 180,
        "speed": 12,
        "temp": 16
      },
      {
        "dir": 200,
        "speed": 9,
        "temp": 9
      },
      {
        "dir": "L&V",
        "speed": "<5",
        "temp": -4
      },
      {
        "dir": 360,
        "speed": 17,
        "temp": -17
      }
    ],
    "ONT_24": [
      {
        "dir": "L&V",
        "speed": "<5",
        "temp": null
      },
      {
        "dir": 250,
        "speed": 7,
        "temp": 22
      },
      {
        "dir": "L&V",
        "speed": "<5",
        "temp": 17
      },
      {
        "dir": 140,
        "speed": 5,
        "temp": 10
      },
      {
        "dir": 220,
        "speed": 7,
        "temp": -5
      },
      {
        "dir": 320,
        "speed": 5,
        "temp": -17
      }
    ],
    "WJF_24": [
      {
        "dir": 280,
        "speed": 10,
        "temp": 22
      },
      {
        "dir": 280,
        "speed": 10,
        "temp": 22
      },
      {
        "dir": 190,
        "speed": 5,
        "temp": 17
      },
      {
        "dir": 160,
        "speed": 9,
        "temp": 10
      },
      {
        "dir": "L&V",
        "speed": "<5",
        "temp": -5
      },
      {
        "dir": 320,
        "speed": 9,
        "temp": -17
      }
    ],
    "SBA_24": [
      {
        "dir": "L&V",
        "speed": "<5",
        "temp": null
      },
      {
        "dir": 30,
        "speed": 6,
        "temp": 21
      },
      {
        "dir": 60,
        "speed": 6,
        "temp": 15
      },
      {
        "dir": "L&V",
        "speed": "<5",
        "temp": 9
      },
      {
        "dir": "L&V",
        "speed": "<5",
        "temp": -5
      },
      {
        "dir": 330,
        "speed": 10,
        "temp": -18
      }
    ],
    "SAN_24": [
      {
        "dir": "L&V",
        "speed": "<5",
        "temp": null
      },
      {
        "dir": 230,
        "speed": 9,
        "temp": 21
      },
      {
        "dir": "L&V",
        "speed": "<5",
        "temp": 16
      },
      {
        "dir": "L&V",
        "speed": "<5",
        "temp": 9
      },
      {
        "dir": "L&V",
        "speed": "<5",
        "temp": -5
      },
      {
        "dir": 60,
        "speed": 6,
        "temp": -18
      }
    ]
  }
}
