{
  "updated": "2026-03-31T22:54:59.722Z",
  "winds": {
    "ONT_06": [
      {
        "dir": 250,
        "speed": 8,
        "temp": null
      },
      {
        "dir": 260,
        "speed": 17,
        "temp": 10
      },
      {
        "dir": 240,
        "speed": 18,
        "temp": 3
      },
      {
        "dir": 210,
        "speed": 30,
        "temp": -4
      },
      {
        "dir": 240,
        "speed": 59,
        "temp": -12
      },
      {
        "dir": 250,
        "speed": 66,
        "temp": -23
      }
    ],
    "WJF_06": [
      {
        "dir": 250,
        "speed": 27,
        "temp": 9
      },
      {
        "dir": 250,
        "speed": 27,
        "temp": 9
      },
      {
        "dir": 240,
        "speed": 24,
        "temp": 1
      },
      {
        "dir": 230,
        "speed": 30,
        "temp": -4
      },
      {
        "dir": 240,
        "speed": 30,
        "temp": -15
      },
      {
        "dir": 240,
        "speed": 58,
        "temp": -24
      }
    ],
    "SBA_06": [
      {
        "dir": 140,
        "speed": 8,
        "temp": null
      },
      {
        "dir": 220,
        "speed": 16,
        "temp": 8
      },
      {
        "dir": 240,
        "speed": 25,
        "temp": 1
      },
      {
        "dir": 260,
        "speed": 33,
        "temp": -3
      },
      {
        "dir": 250,
        "speed": 50,
        "temp": -15
      },
      {
        "dir": 240,
        "speed": 65,
        "temp": -25
      }
    ],
    "SAN_06": [
      {
        "dir": 190,
        "speed": 15,
        "temp": null
      },
      {
        "dir": 230,
        "speed": 18,
        "temp": 13
      },
      {
        "dir": 250,
        "speed": 18,
        "temp": 7
      },
      {
        "dir": 230,
        "speed": 27,
        "temp": -2
      },
      {
        "dir": 240,
        "speed": 50,
        "temp": -12
      },
      {
        "dir": 260,
        "speed": 64,
        "temp": -22
      }
    ],
    "ONT_12": [
      {
        "dir": 210,
        "speed": 5,
        "temp": null
      },
      {
        "dir": 250,
        "speed": 23,
        "temp": 6
      },
      {
        "dir": 260,
        "speed": 27,
        "temp": 1
      },
      {
        "dir": 260,
        "speed": 40,
        "temp": -4
      },
      {
        "dir": 240,
        "speed": 58,
        "temp": -14
      },
      {
        "dir": 240,
        "speed": 71,
        "temp": -25
      }
    ],
    "WJF_12": [
      {
        "dir": 260,
        "speed": 25,
        "temp": 6
      },
      {
        "dir": 260,
        "speed": 25,
        "temp": 6
      },
      {
        "dir": 250,
        "speed": 28,
        "temp": 1
      },
      {
        "dir": 260,
        "speed": 29,
        "temp": -5
      },
      {
        "dir": 240,
        "speed": 60,
        "temp": -18
      },
      {
        "dir": 240,
        "speed": 85,
        "temp": -27
      }
    ],
    "SBA_12": [
      {
        "dir": 180,
        "speed": 6,
        "temp": null
      },
      {
        "dir": 230,
        "speed": 21,
        "temp": 5
      },
      {
        "dir": 260,
        "speed": 26,
        "temp": -1
      },
      {
        "dir": 260,
        "speed": 33,
        "temp": -5
      },
      {
        "dir": 260,
        "speed": 49,
        "temp": -19
      },
      {
        "dir": 250,
        "speed": 70,
        "temp": -28
      }
    ],
    "SAN_12": [
      {
        "dir": 350,
        "speed": 7,
        "temp": null
      },
      {
        "dir": 270,
        "speed": 22,
        "temp": 10
      },
      {
        "dir": 240,
        "speed": 37,
        "temp": 4
      },
      {
        "dir": 250,
        "speed": 41,
        "temp": -3
      },
      {
        "dir": 240,
        "speed": 57,
        "temp": -13
      },
      {
        "dir": 250,
        "speed": 71,
        "temp": -22
      }
    ],
    "ONT_24": [
      {
        "dir": 200,
        "speed": 5,
        "temp": null
      },
      {
        "dir": 270,
        "speed": 18,
        "temp": 5
      },
      {
        "dir": 280,
        "speed": 26,
        "temp": 3
      },
      {
        "dir": 280,
        "speed": 31,
        "temp": -1
      },
      {
        "dir": 290,
        "speed": 46,
        "temp": -14
      },
      {
        "dir": 300,
        "speed": 59,
        "temp": -27
      }
    ],
    "WJF_24": [
      {
        "dir": 280,
        "speed": 20,
        "temp": 5
      },
      {
        "dir": 280,
        "speed": 20,
        "temp": 5
      },
      {
        "dir": 290,
        "speed": 23,
        "temp": 3
      },
      {
        "dir": 280,
        "speed": 29,
        "temp": -1
      },
      {
        "dir": 290,
        "speed": 44,
        "temp": -14
      },
      {
        "dir": 300,
        "speed": 62,
        "temp": -27
      }
    ],
    "SBA_24": [
      {
        "dir": 320,
        "speed": 5,
        "temp": null
      },
      {
        "dir": 300,
        "speed": 15,
        "temp": 6
      },
      {
        "dir": 290,
        "speed": 22,
        "temp": 3
      },
      {
        "dir": 280,
        "speed": 31,
        "temp": -1
      },
      {
        "dir": 290,
        "speed": 46,
        "temp": -14
      },
      {
        "dir": 300,
        "speed": 62,
        "temp": -26
      }
    ],
    "SAN_24": [
      {
        "dir": 220,
        "speed": 11,
        "temp": null
      },
      {
        "dir": 290,
        "speed": 18,
        "temp": 6
      },
      {
        "dir": 290,
        "speed": 28,
        "temp": 5
      },
      {
        "dir": 280,
        "speed": 32,
        "temp": 1
      },
      {
        "dir": 290,
        "speed": 47,
        "temp": -13
      },
      {
        "dir": 300,
        "speed": 55,
        "temp": -26
      }
    ]
  }
}
