{
  "updated": "2026-04-30T15:11:34.989Z",
  "winds": {
    "ONT_06": [
      {
        "dir": "L&V",
        "speed": "<5",
        "temp": null
      },
      {
        "dir": 60,
        "speed": 14,
        "temp": 13
      },
      {
        "dir": 80,
        "speed": 9,
        "temp": 5
      },
      {
        "dir": 80,
        "speed": 7,
        "temp": -3
      },
      {
        "dir": 40,
        "speed": 20,
        "temp": -15
      },
      {
        "dir": 50,
        "speed": 29,
        "temp": -26
      }
    ],
    "WJF_06": [
      {
        "dir": 60,
        "speed": 18,
        "temp": 12
      },
      {
        "dir": 60,
        "speed": 18,
        "temp": 12
      },
      {
        "dir": 70,
        "speed": 13,
        "temp": 5
      },
      {
        "dir": 60,
        "speed": 6,
        "temp": -3
      },
      {
        "dir": 20,
        "speed": 24,
        "temp": -13
      },
      {
        "dir": 30,
        "speed": 23,
        "temp": -26
      }
    ],
    "SBA_06": [
      {
        "dir": 340,
        "speed": 5,
        "temp": null
      },
      {
        "dir": 50,
        "speed": 9,
        "temp": 11
      },
      {
        "dir": 90,
        "speed": 10,
        "temp": 5
      },
      {
        "dir": 70,
        "speed": 8,
        "temp": -2
      },
      {
        "dir": 360,
        "speed": 30,
        "temp": -13
      },
      {
        "dir": 20,
        "speed": 23,
        "temp": -25
      }
    ],
    "SAN_06": [
      {
        "dir": "L&V",
        "speed": "<5",
        "temp": null
      },
      {
        "dir": 60,
        "speed": 11,
        "temp": 11
      },
      {
        "dir": 90,
        "speed": 10,
        "temp": 5
      },
      {
        "dir": 120,
        "speed": 9,
        "temp": -3
      },
      {
        "dir": 50,
        "speed": 7,
        "temp": -16
      },
      {
        "dir": 50,
        "speed": 22,
        "temp": -29
      }
    ],
    "ONT_12": [
      {
        "dir": 240,
        "speed": 9,
        "temp": null
      },
      {
        "dir": 300,
        "speed": 8,
        "temp": 14
      },
      {
        "dir": 340,
        "speed": 11,
        "temp": 6
      },
      {
        "dir": 360,
        "speed": 13,
        "temp": -2
      },
      {
        "dir": 360,
        "speed": 26,
        "temp": -13
      },
      {
        "dir": 350,
        "speed": 29,
        "temp": -25
      }
    ],
    "WJF_12": [
      {
        "dir": 340,
        "speed": 6,
        "temp": 15
      },
      {
        "dir": 340,
        "speed": 6,
        "temp": 15
      },
      {
        "dir": 360,
        "speed": 6,
        "temp": 6
      },
      {
        "dir": 10,
        "speed": 10,
        "temp": -2
      },
      {
        "dir": 350,
        "speed": 21,
        "temp": -12
      },
      {
        "dir": 340,
        "speed": 27,
        "temp": -25
      }
    ],
    "SBA_12": [
      {
        "dir": 320,
        "speed": 9,
        "temp": null
      },
      {
        "dir": 360,
        "speed": 10,
        "temp": 13
      },
      {
        "dir": 30,
        "speed": 5,
        "temp": 5
      },
      {
        "dir": 20,
        "speed": 9,
        "temp": -1
      },
      {
        "dir": 350,
        "speed": 23,
        "temp": -12
      },
      {
        "dir": 330,
        "speed": 27,
        "temp": -25
      }
    ],
    "SAN_12": [
      {
        "dir": "L&V",
        "speed": "<5",
        "temp": null
      },
      {
        "dir": 340,
        "speed": 5,
        "temp": 13
      },
      {
        "dir": 30,
        "speed": 12,
        "temp": 6
      },
      {
        "dir": 10,
        "speed": 15,
        "temp": -2
      },
      {
        "dir": 20,
        "speed": 25,
        "temp": -14
      },
      {
        "dir": 10,
        "speed": 40,
        "temp": -25
      }
    ],
    "ONT_24": [
      {
        "dir": "L&V",
        "speed": "<5",
        "temp": null
      },
      {
        "dir": 10,
        "speed": 6,
        "temp": 14
      },
      {
        "dir": 10,
        "speed": 5,
        "temp": 6
      },
      {
        "dir": 360,
        "speed": 9,
        "temp": -1
      },
      {
        "dir": 310,
        "speed": 26,
        "temp": -13
      },
      {
        "dir": 320,
        "speed": 34,
        "temp": -24
      }
    ],
    "WJF_24": [
      {
        "dir": 40,
        "speed": 7,
        "temp": 13
      },
      {
        "dir": 40,
        "speed": 7,
        "temp": 13
      },
      {
        "dir": "L&V",
        "speed": "<5",
        "temp": 6
      },
      {
        "dir": 300,
        "speed": 6,
        "temp": -2
      },
      {
        "dir": 310,
        "speed": 26,
        "temp": -13
      },
      {
        "dir": 310,
        "speed": 37,
        "temp": -25
      }
    ],
    "SBA_24": [
      {
        "dir": "L&V",
        "speed": "<5",
        "temp": null
      },
      {
        "dir": 350,
        "speed": 8,
        "temp": 13
      },
      {
        "dir": "L&V",
        "speed": "<5",
        "temp": 6
      },
      {
        "dir": 320,
        "speed": 9,
        "temp": 1
      },
      {
        "dir": 310,
        "speed": 21,
        "temp": -12
      },
      {
        "dir": 310,
        "speed": 26,
        "temp": -24
      }
    ],
    "SAN_24": [
      {
        "dir": 340,
        "speed": 6,
        "temp": null
      },
      {
        "dir": 350,
        "speed": 15,
        "temp": 13
      },
      {
        "dir": 360,
        "speed": 7,
        "temp": 7
      },
      {
        "dir": 330,
        "speed": 7,
        "temp": 0
      },
      {
        "dir": 310,
        "speed": 26,
        "temp": -12
      },
      {
        "dir": 310,
        "speed": 36,
        "temp": -24
      }
    ]
  }
}
