{
  "updated": "2026-07-14T17:00:14.417Z",
  "winds": {
    "ONT_06": [
      {
        "dir": "L&V",
        "speed": "<5",
        "temp": null
      },
      {
        "dir": "L&V",
        "speed": "<5",
        "temp": 22
      },
      {
        "dir": "L&V",
        "speed": "<5",
        "temp": 14
      },
      {
        "dir": "L&V",
        "speed": "<5",
        "temp": 7
      },
      {
        "dir": 170,
        "speed": 17,
        "temp": -5
      },
      {
        "dir": 190,
        "speed": 14,
        "temp": -15
      }
    ],
    "WJF_06": [
      {
        "dir": "L&V",
        "speed": "<5",
        "temp": 21
      },
      {
        "dir": "L&V",
        "speed": "<5",
        "temp": 21
      },
      {
        "dir": 280,
        "speed": 6,
        "temp": 14
      },
      {
        "dir": 240,
        "speed": 7,
        "temp": 7
      },
      {
        "dir": 180,
        "speed": 20,
        "temp": -5
      },
      {
        "dir": 200,
        "speed": 22,
        "temp": -16
      }
    ],
    "SBA_06": [
      {
        "dir": 310,
        "speed": 5,
        "temp": null
      },
      {
        "dir": 360,
        "speed": 7,
        "temp": 21
      },
      {
        "dir": "L&V",
        "speed": "<5",
        "temp": 14
      },
      {
        "dir": "L&V",
        "speed": "<5",
        "temp": 7
      },
      {
        "dir": 190,
        "speed": 19,
        "temp": -7
      },
      {
        "dir": 200,
        "speed": 34,
        "temp": -18
      }
    ],
    "SAN_06": [
      {
        "dir": 350,
        "speed": 9,
        "temp": null
      },
      {
        "dir": "L&V",
        "speed": "<5",
        "temp": 21
      },
      {
        "dir": "L&V",
        "speed": "<5",
        "temp": 14
      },
      {
        "dir": "L&V",
        "speed": "<5",
        "temp": 8
      },
      {
        "dir": 180,
        "speed": 16,
        "temp": -5
      },
      {
        "dir": 170,
        "speed": 15,
        "temp": -15
      }
    ],
    "ONT_12": [
      {
        "dir": 250,
        "speed": 10,
        "temp": null
      },
      {
        "dir": 260,
        "speed": 5,
        "temp": 23
      },
      {
        "dir": 10,
        "speed": 5,
        "temp": 16
      },
      {
        "dir": 60,
        "speed": 6,
        "temp": 9
      },
      {
        "dir": 200,
        "speed": 11,
        "temp": -5
      },
      {
        "dir": 200,
        "speed": 13,
        "temp": -15
      }
    ],
    "WJF_12": [
      {
        "dir": 280,
        "speed": 11,
        "temp": 24
      },
      {
        "dir": 280,
        "speed": 11,
        "temp": 24
      },
      {
        "dir": 290,
        "speed": 9,
        "temp": 16
      },
      {
        "dir": "L&V",
        "speed": "<5",
        "temp": 8
      },
      {
        "dir": 200,
        "speed": 11,
        "temp": -5
      },
      {
        "dir": 200,
        "speed": 24,
        "temp": -16
      }
    ],
    "SBA_12": [
      {
        "dir": 300,
        "speed": 11,
        "temp": null
      },
      {
        "dir": 340,
        "speed": 11,
        "temp": 23
      },
      {
        "dir": 360,
        "speed": 10,
        "temp": 15
      },
      {
        "dir": "L&V",
        "speed": "<5",
        "temp": 7
      },
      {
        "dir": 210,
        "speed": 12,
        "temp": -6
      },
      {
        "dir": 210,
        "speed": 31,
        "temp": -16
      }
    ],
    "SAN_12": [
      {
        "dir": 320,
        "speed": 11,
        "temp": null
      },
      {
        "dir": 340,
        "speed": 5,
        "temp": 22
      },
      {
        "dir": "L&V",
        "speed": "<5",
        "temp": 15
      },
      {
        "dir": 100,
        "speed": 7,
        "temp": 9
      },
      {
        "dir": 180,
        "speed": 8,
        "temp": -4
      },
      {
        "dir": 180,
        "speed": 11,
        "temp": -15
      }
    ],
    "ONT_24": [
      {
        "dir": 340,
        "speed": 5,
        "temp": null
      },
      {
        "dir": 310,
        "speed": 7,
        "temp": 23
      },
      {
        "dir": "L&V",
        "speed": "<5",
        "temp": 16
      },
      {
        "dir": 130,
        "speed": 6,
        "temp": 9
      },
      {
        "dir": 190,
        "speed": 8,
        "temp": -5
      },
      {
        "dir": 250,
        "speed": 15,
        "temp": -16
      }
    ],
    "WJF_24": [
      {
        "dir": 350,
        "speed": 13,
        "temp": 23
      },
      {
        "dir": 350,
        "speed": 13,
        "temp": 23
      },
      {
        "dir": 280,
        "speed": 6,
        "temp": 16
      },
      {
        "dir": 200,
        "speed": 7,
        "temp": 9
      },
      {
        "dir": 210,
        "speed": 14,
        "temp": -5
      },
      {
        "dir": 230,
        "speed": 25,
        "temp": -17
      }
    ],
    "SBA_24": [
      {
        "dir": 20,
        "speed": 12,
        "temp": null
      },
      {
        "dir": 350,
        "speed": 12,
        "temp": 22
      },
      {
        "dir": 320,
        "speed": 7,
        "temp": 15
      },
      {
        "dir": "L&V",
        "speed": "<5",
        "temp": 9
      },
      {
        "dir": 210,
        "speed": 14,
        "temp": -6
      },
      {
        "dir": 220,
        "speed": 18,
        "temp": -17
      }
    ],
    "SAN_24": [
      {
        "dir": 320,
        "speed": 9,
        "temp": null
      },
      {
        "dir": 330,
        "speed": 9,
        "temp": 23
      },
      {
        "dir": "L&V",
        "speed": "<5",
        "temp": 15
      },
      {
        "dir": "L&V",
        "speed": "<5",
        "temp": 9
      },
      {
        "dir": 140,
        "speed": 7,
        "temp": -5
      },
      {
        "dir": 340,
        "speed": 8,
        "temp": -16
      }
    ]
  }
}
