{
  "updated": "2026-03-31T05:58:47.126Z",
  "winds": {
    "ONT_06": [
      {
        "dir": "L&V",
        "speed": "<5",
        "temp": null
      },
      {
        "dir": 250,
        "speed": 15,
        "temp": 15
      },
      {
        "dir": 250,
        "speed": 23,
        "temp": 8
      },
      {
        "dir": 250,
        "speed": 33,
        "temp": 1
      },
      {
        "dir": 240,
        "speed": 41,
        "temp": -16
      },
      {
        "dir": 250,
        "speed": 43,
        "temp": -23
      }
    ],
    "WJF_06": [
      {
        "dir": 250,
        "speed": 14,
        "temp": 14
      },
      {
        "dir": 250,
        "speed": 14,
        "temp": 14
      },
      {
        "dir": 250,
        "speed": 20,
        "temp": 8
      },
      {
        "dir": 250,
        "speed": 28,
        "temp": 1
      },
      {
        "dir": 240,
        "speed": 49,
        "temp": -15
      },
      {
        "dir": 250,
        "speed": 47,
        "temp": -24
      }
    ],
    "SBA_06": [
      {
        "dir": "L&V",
        "speed": "<5",
        "temp": null
      },
      {
        "dir": 230,
        "speed": 8,
        "temp": 14
      },
      {
        "dir": 240,
        "speed": 13,
        "temp": 7
      },
      {
        "dir": 230,
        "speed": 21,
        "temp": -1
      },
      {
        "dir": 240,
        "speed": 44,
        "temp": -14
      },
      {
        "dir": 250,
        "speed": 54,
        "temp": -23
      }
    ],
    "SAN_06": [
      {
        "dir": 180,
        "speed": 13,
        "temp": null
      },
      {
        "dir": 240,
        "speed": 12,
        "temp": 17
      },
      {
        "dir": 250,
        "speed": 19,
        "temp": 10
      },
      {
        "dir": 240,
        "speed": 29,
        "temp": 3
      },
      {
        "dir": 240,
        "speed": 35,
        "temp": -14
      },
      {
        "dir": 260,
        "speed": 43,
        "temp": -22
      }
    ],
    "ONT_12": [
      {
        "dir": "L&V",
        "speed": "<5",
        "temp": null
      },
      {
        "dir": 240,
        "speed": 14,
        "temp": 13
      },
      {
        "dir": 240,
        "speed": 25,
        "temp": 7
      },
      {
        "dir": 240,
        "speed": 35,
        "temp": 0
      },
      {
        "dir": 250,
        "speed": 50,
        "temp": -14
      },
      {
        "dir": 260,
        "speed": 57,
        "temp": -24
      }
    ],
    "WJF_12": [
      {
        "dir": 250,
        "speed": 17,
        "temp": 13
      },
      {
        "dir": 250,
        "speed": 17,
        "temp": 13
      },
      {
        "dir": 240,
        "speed": 22,
        "temp": 7
      },
      {
        "dir": 230,
        "speed": 32,
        "temp": -1
      },
      {
        "dir": 250,
        "speed": 46,
        "temp": -14
      },
      {
        "dir": 260,
        "speed": 53,
        "temp": -25
      }
    ],
    "SBA_12": [
      {
        "dir": "L&V",
        "speed": "<5",
        "temp": null
      },
      {
        "dir": 270,
        "speed": 14,
        "temp": 12
      },
      {
        "dir": 250,
        "speed": 18,
        "temp": 5
      },
      {
        "dir": 230,
        "speed": 26,
        "temp": -2
      },
      {
        "dir": 250,
        "speed": 39,
        "temp": -14
      },
      {
        "dir": 260,
        "speed": 49,
        "temp": -26
      }
    ],
    "SAN_12": [
      {
        "dir": 180,
        "speed": 16,
        "temp": null
      },
      {
        "dir": 240,
        "speed": 13,
        "temp": 16
      },
      {
        "dir": 230,
        "speed": 25,
        "temp": 9
      },
      {
        "dir": 230,
        "speed": 31,
        "temp": 2
      },
      {
        "dir": 250,
        "speed": 37,
        "temp": -13
      },
      {
        "dir": 260,
        "speed": 52,
        "temp": -22
      }
    ],
    "ONT_24": [
      {
        "dir": 270,
        "speed": 11,
        "temp": null
      },
      {
        "dir": 260,
        "speed": 25,
        "temp": 9
      },
      {
        "dir": 250,
        "speed": 47,
        "temp": 1
      },
      {
        "dir": 250,
        "speed": 48,
        "temp": -4
      },
      {
        "dir": 250,
        "speed": 49,
        "temp": -13
      },
      {
        "dir": 240,
        "speed": 65,
        "temp": -24
      }
    ],
    "WJF_24": [
      {
        "dir": 250,
        "speed": 33,
        "temp": 7
      },
      {
        "dir": 250,
        "speed": 33,
        "temp": 7
      },
      {
        "dir": 250,
        "speed": 39,
        "temp": 1
      },
      {
        "dir": 270,
        "speed": 34,
        "temp": -4
      },
      {
        "dir": 250,
        "speed": 54,
        "temp": -15
      },
      {
        "dir": 230,
        "speed": 73,
        "temp": -24
      }
    ],
    "SBA_24": [
      {
        "dir": 280,
        "speed": 7,
        "temp": null
      },
      {
        "dir": 270,
        "speed": 25,
        "temp": 7
      },
      {
        "dir": 250,
        "speed": 29,
        "temp": 1
      },
      {
        "dir": 270,
        "speed": 35,
        "temp": -4
      },
      {
        "dir": 260,
        "speed": 59,
        "temp": -17
      },
      {
        "dir": 250,
        "speed": 85,
        "temp": -24
      }
    ],
    "SAN_24": [
      {
        "dir": "L&V",
        "speed": "<5",
        "temp": null
      },
      {
        "dir": 270,
        "speed": 11,
        "temp": 12
      },
      {
        "dir": 240,
        "speed": 27,
        "temp": 6
      },
      {
        "dir": 240,
        "speed": 41,
        "temp": 0
      },
      {
        "dir": 250,
        "speed": 48,
        "temp": -12
      },
      {
        "dir": 260,
        "speed": 65,
        "temp": -21
      }
    ]
  }
}
