{
  "updated": "2026-06-02T11:46:10.318Z",
  "winds": {
    "ONT_06": [
      {
        "dir": "L&V",
        "speed": "<5",
        "temp": null
      },
      {
        "dir": 50,
        "speed": 5,
        "temp": 18
      },
      {
        "dir": 120,
        "speed": 12,
        "temp": 12
      },
      {
        "dir": 150,
        "speed": 7,
        "temp": 6
      },
      {
        "dir": 210,
        "speed": 8,
        "temp": -10
      },
      {
        "dir": 240,
        "speed": 9,
        "temp": -22
      }
    ],
    "WJF_06": [
      {
        "dir": 350,
        "speed": 5,
        "temp": 18
      },
      {
        "dir": 350,
        "speed": 5,
        "temp": 18
      },
      {
        "dir": 100,
        "speed": 5,
        "temp": 11
      },
      {
        "dir": 170,
        "speed": 7,
        "temp": 6
      },
      {
        "dir": "L&V",
        "speed": "<5",
        "temp": -10
      },
      {
        "dir": 240,
        "speed": 8,
        "temp": -23
      }
    ],
    "SBA_06": [
      {
        "dir": 10,
        "speed": 5,
        "temp": null
      },
      {
        "dir": 20,
        "speed": 13,
        "temp": 15
      },
      {
        "dir": 50,
        "speed": 6,
        "temp": 11
      },
      {
        "dir": "L&V",
        "speed": "<5",
        "temp": 5
      },
      {
        "dir": 180,
        "speed": 5,
        "temp": -10
      },
      {
        "dir": 210,
        "speed": 8,
        "temp": -23
      }
    ],
    "SAN_06": [
      {
        "dir": "L&V",
        "speed": "<5",
        "temp": null
      },
      {
        "dir": 160,
        "speed": 8,
        "temp": 18
      },
      {
        "dir": 160,
        "speed": 5,
        "temp": 13
      },
      {
        "dir": 190,
        "speed": 7,
        "temp": 6
      },
      {
        "dir": 210,
        "speed": 14,
        "temp": -10
      },
      {
        "dir": 240,
        "speed": 13,
        "temp": -22
      }
    ],
    "ONT_12": [
      {
        "dir": "L&V",
        "speed": "<5",
        "temp": null
      },
      {
        "dir": 110,
        "speed": 11,
        "temp": 18
      },
      {
        "dir": 140,
        "speed": 15,
        "temp": 12
      },
      {
        "dir": 150,
        "speed": 5,
        "temp": 6
      },
      {
        "dir": 200,
        "speed": 9,
        "temp": -10
      },
      {
        "dir": 200,
        "speed": 5,
        "temp": -22
      }
    ],
    "WJF_12": [
      {
        "dir": 70,
        "speed": 5,
        "temp": 18
      },
      {
        "dir": 70,
        "speed": 5,
        "temp": 18
      },
      {
        "dir": 120,
        "speed": 11,
        "temp": 12
      },
      {
        "dir": 120,
        "speed": 6,
        "temp": 5
      },
      {
        "dir": "L&V",
        "speed": "<5",
        "temp": -10
      },
      {
        "dir": "L&V",
        "speed": "<5",
        "temp": -22
      }
    ],
    "SBA_12": [
      {
        "dir": "L&V",
        "speed": "<5",
        "temp": null
      },
      {
        "dir": 50,
        "speed": 7,
        "temp": 17
      },
      {
        "dir": 100,
        "speed": 9,
        "temp": 11
      },
      {
        "dir": 80,
        "speed": 6,
        "temp": 5
      },
      {
        "dir": 80,
        "speed": 5,
        "temp": -10
      },
      {
        "dir": 120,
        "speed": 6,
        "temp": -23
      }
    ],
    "SAN_12": [
      {
        "dir": 100,
        "speed": 5,
        "temp": null
      },
      {
        "dir": 140,
        "speed": 13,
        "temp": 18
      },
      {
        "dir": 140,
        "speed": 14,
        "temp": 13
      },
      {
        "dir": 160,
        "speed": 9,
        "temp": 6
      },
      {
        "dir": 210,
        "speed": 11,
        "temp": -10
      },
      {
        "dir": 240,
        "speed": 17,
        "temp": -21
      }
    ],
    "ONT_24": [
      {
        "dir": "L&V",
        "speed": "<5",
        "temp": null
      },
      {
        "dir": "L&V",
        "speed": "<5",
        "temp": 19
      },
      {
        "dir": 70,
        "speed": 5,
        "temp": 13
      },
      {
        "dir": 90,
        "speed": 11,
        "temp": 6
      },
      {
        "dir": 160,
        "speed": 10,
        "temp": -9
      },
      {
        "dir": 130,
        "speed": 6,
        "temp": -21
      }
    ],
    "WJF_24": [
      {
        "dir": 270,
        "speed": 10,
        "temp": 20
      },
      {
        "dir": 270,
        "speed": 10,
        "temp": 20
      },
      {
        "dir": "L&V",
        "speed": "<5",
        "temp": 13
      },
      {
        "dir": 120,
        "speed": 10,
        "temp": 6
      },
      {
        "dir": 140,
        "speed": 6,
        "temp": -9
      },
      {
        "dir": 80,
        "speed": 7,
        "temp": -21
      }
    ],
    "SBA_24": [
      {
        "dir": 20,
        "speed": 7,
        "temp": null
      },
      {
        "dir": 30,
        "speed": 12,
        "temp": 18
      },
      {
        "dir": 60,
        "speed": 5,
        "temp": 12
      },
      {
        "dir": "L&V",
        "speed": "<5",
        "temp": 6
      },
      {
        "dir": 70,
        "speed": 10,
        "temp": -9
      },
      {
        "dir": 50,
        "speed": 13,
        "temp": -21
      }
    ],
    "SAN_24": [
      {
        "dir": "L&V",
        "speed": "<5",
        "temp": null
      },
      {
        "dir": "L&V",
        "speed": "<5",
        "temp": 19
      },
      {
        "dir": 110,
        "speed": 8,
        "temp": 12
      },
      {
        "dir": 90,
        "speed": 8,
        "temp": 7
      },
      {
        "dir": 140,
        "speed": 12,
        "temp": -9
      },
      {
        "dir": 180,
        "speed": 11,
        "temp": -22
      }
    ]
  }
}
